{
  "id": "0ab24dcb-8abc-4bed-8a59-bdf9f967eb4a",
  "prevId": "00000000-0000-0000-0000-000000000000",
  "version": "7",
  "dialect": "postgresql",
  "tables": {
    "public.page_index_status": {
      "name": "page_index_status",
      "schema": "",
      "columns": {
        "id": {
          "name": "id",
          "type": "text",
          "primaryKey": true,
          "notNull": true
        },
        "site_id": {
          "name": "site_id",
          "type": "text",
          "primaryKey": false,
          "notNull": true
        },
        "page": {
          "name": "page",
          "type": "text",
          "primaryKey": false,
          "notNull": true
        },
        "verdict": {
          "name": "verdict",
          "type": "text",
          "primaryKey": false,
          "notNull": true
        },
        "coverage_state": {
          "name": "coverage_state",
          "type": "text",
          "primaryKey": false,
          "notNull": false
        },
        "indexing_state": {
          "name": "indexing_state",
          "type": "text",
          "primaryKey": false,
          "notNull": false
        },
        "page_fetch_state": {
          "name": "page_fetch_state",
          "type": "text",
          "primaryKey": false,
          "notNull": false
        },
        "last_crawl_time": {
          "name": "last_crawl_time",
          "type": "timestamp",
          "primaryKey": false,
          "notNull": false
        },
        "robots_txt_state": {
          "name": "robots_txt_state",
          "type": "text",
          "primaryKey": false,
          "notNull": false
        },
        "fetched_at": {
          "name": "fetched_at",
          "type": "timestamp",
          "primaryKey": false,
          "notNull": false,
          "default": "now()"
        }
      },
      "indexes": {
        "page_index_site_idx": {
          "name": "page_index_site_idx",
          "columns": [
            {
              "expression": "site_id",
              "isExpression": false,
              "asc": true,
              "nulls": "last"
            },
            {
              "expression": "page",
              "isExpression": false,
              "asc": true,
              "nulls": "last"
            }
          ],
          "isUnique": false,
          "concurrently": false,
          "method": "btree",
          "with": {}
        }
      },
      "foreignKeys": {},
      "compositePrimaryKeys": {},
      "uniqueConstraints": {},
      "policies": {},
      "checkConstraints": {},
      "isRLSEnabled": false
    },
    "public.query_analytics": {
      "name": "query_analytics",
      "schema": "",
      "columns": {
        "id": {
          "name": "id",
          "type": "text",
          "primaryKey": true,
          "notNull": true
        },
        "site_id": {
          "name": "site_id",
          "type": "text",
          "primaryKey": false,
          "notNull": true
        },
        "page": {
          "name": "page",
          "type": "text",
          "primaryKey": false,
          "notNull": true
        },
        "query": {
          "name": "query",
          "type": "text",
          "primaryKey": false,
          "notNull": true
        },
        "date": {
          "name": "date",
          "type": "date",
          "primaryKey": false,
          "notNull": true
        },
        "clicks": {
          "name": "clicks",
          "type": "integer",
          "primaryKey": false,
          "notNull": true,
          "default": 0
        },
        "impressions": {
          "name": "impressions",
          "type": "integer",
          "primaryKey": false,
          "notNull": true,
          "default": 0
        },
        "ctr": {
          "name": "ctr",
          "type": "real",
          "primaryKey": false,
          "notNull": true,
          "default": 0
        },
        "position": {
          "name": "position",
          "type": "real",
          "primaryKey": false,
          "notNull": true,
          "default": 0
        }
      },
      "indexes": {
        "site_page_query_idx": {
          "name": "site_page_query_idx",
          "columns": [
            {
              "expression": "site_id",
              "isExpression": false,
              "asc": true,
              "nulls": "last"
            },
            {
              "expression": "page",
              "isExpression": false,
              "asc": true,
              "nulls": "last"
            },
            {
              "expression": "query",
              "isExpression": false,
              "asc": true,
              "nulls": "last"
            }
          ],
          "isUnique": false,
          "concurrently": false,
          "method": "btree",
          "with": {}
        }
      },
      "foreignKeys": {},
      "compositePrimaryKeys": {},
      "uniqueConstraints": {},
      "policies": {},
      "checkConstraints": {},
      "isRLSEnabled": false
    },
    "public.search_analytics": {
      "name": "search_analytics",
      "schema": "",
      "columns": {
        "id": {
          "name": "id",
          "type": "text",
          "primaryKey": true,
          "notNull": true
        },
        "site_id": {
          "name": "site_id",
          "type": "text",
          "primaryKey": false,
          "notNull": true
        },
        "page": {
          "name": "page",
          "type": "text",
          "primaryKey": false,
          "notNull": true
        },
        "date": {
          "name": "date",
          "type": "date",
          "primaryKey": false,
          "notNull": true
        },
        "clicks": {
          "name": "clicks",
          "type": "integer",
          "primaryKey": false,
          "notNull": true,
          "default": 0
        },
        "impressions": {
          "name": "impressions",
          "type": "integer",
          "primaryKey": false,
          "notNull": true,
          "default": 0
        },
        "ctr": {
          "name": "ctr",
          "type": "real",
          "primaryKey": false,
          "notNull": true,
          "default": 0
        },
        "position": {
          "name": "position",
          "type": "real",
          "primaryKey": false,
          "notNull": true,
          "default": 0
        },
        "fetched_at": {
          "name": "fetched_at",
          "type": "timestamp",
          "primaryKey": false,
          "notNull": false,
          "default": "now()"
        }
      },
      "indexes": {
        "site_page_idx": {
          "name": "site_page_idx",
          "columns": [
            {
              "expression": "site_id",
              "isExpression": false,
              "asc": true,
              "nulls": "last"
            },
            {
              "expression": "page",
              "isExpression": false,
              "asc": true,
              "nulls": "last"
            }
          ],
          "isUnique": false,
          "concurrently": false,
          "method": "btree",
          "with": {}
        },
        "site_date_idx": {
          "name": "site_date_idx",
          "columns": [
            {
              "expression": "site_id",
              "isExpression": false,
              "asc": true,
              "nulls": "last"
            },
            {
              "expression": "date",
              "isExpression": false,
              "asc": true,
              "nulls": "last"
            }
          ],
          "isUnique": false,
          "concurrently": false,
          "method": "btree",
          "with": {}
        }
      },
      "foreignKeys": {},
      "compositePrimaryKeys": {},
      "uniqueConstraints": {},
      "policies": {},
      "checkConstraints": {},
      "isRLSEnabled": false
    },
    "public.sync_log": {
      "name": "sync_log",
      "schema": "",
      "columns": {
        "id": {
          "name": "id",
          "type": "text",
          "primaryKey": true,
          "notNull": true
        },
        "site_id": {
          "name": "site_id",
          "type": "text",
          "primaryKey": false,
          "notNull": true
        },
        "started_at": {
          "name": "started_at",
          "type": "timestamp",
          "primaryKey": false,
          "notNull": true
        },
        "completed_at": {
          "name": "completed_at",
          "type": "timestamp",
          "primaryKey": false,
          "notNull": false
        },
        "rows_processed": {
          "name": "rows_processed",
          "type": "integer",
          "primaryKey": false,
          "notNull": false
        },
        "status": {
          "name": "status",
          "type": "text",
          "primaryKey": false,
          "notNull": true
        },
        "error": {
          "name": "error",
          "type": "text",
          "primaryKey": false,
          "notNull": false
        }
      },
      "indexes": {},
      "foreignKeys": {},
      "compositePrimaryKeys": {},
      "uniqueConstraints": {},
      "policies": {},
      "checkConstraints": {},
      "isRLSEnabled": false
    }
  },
  "enums": {},
  "schemas": {},
  "sequences": {},
  "roles": {},
  "policies": {},
  "views": {},
  "_meta": {
    "columns": {},
    "schemas": {},
    "tables": {}
  }
}